README.md
setup.cfg
setup.py
MessagingDispatcher.egg-info/PKG-INFO
MessagingDispatcher.egg-info/SOURCES.txt
MessagingDispatcher.egg-info/dependency_links.txt
MessagingDispatcher.egg-info/requires.txt
MessagingDispatcher.egg-info/top_level.txt
messagingdispatcher/__init__.py
messagingdispatcher/config.py
messagingdispatcher/db/__init__.py
messagingdispatcher/db/basedb.py
messagingdispatcher/db/dynamodb.py
messagingdispatcher/db/relationaldb.py
messagingdispatcher/pubsub/__init__.py
messagingdispatcher/pubsub/ablyservice.py
messagingdispatcher/pubsub/pubsubservice.py
messagingdispatcher/queue/__init__.py
messagingdispatcher/queue/sqs.py
messagingdispatcher/search/__init__.py
messagingdispatcher/search/esclient.py
tests/__init__.py
tests/test_ablyservice.py
tests/test_dynamodb.py
tests/test_elasticsearch.py
tests/test_relationaldb.py