Metadata-Version: 1.0
Name: MessagingDispatcher
Version: 0.0.0.8
Summary: A process engine to dispatch messages to various AWS services.
Home-page: UNKNOWN
Author: CarPal Fleet
Author-email: nick@carpal.me
License: Apache License 2.0
Keywords: messaging,aws,pubsub
Platform: any
